{
    "users": [
        {
            "id": 1,
            "name": "Jakyn",
            "email": "jakyn@gmail.com"
        },
        {
            "id": 2,
            "name": "beautifulmouse476",
            "email": "vicente.torres@example.com"
        },
        {
            "id": 3,
            "name": "yellowcat882",
            "email": "justine.ma@example.com"
        },
        {
            "id": 4,
            "name": "brownostrich737",
            "email": "sonke.schwinn@example.com"
        },
        {
            "id": 5,
            "name": "blackduck796",
            "email": "juliocesar.urias@example.com"
        },
        {
            "id": 6,
            "name": "purpleswan273",
            "email": "andrijana.malesevic@example.com"
        },
        {
            "id": 7,
            "name": "greenrabbit317",
            "email": "fatima.delgado@example.com"
        },
        {
            "id": 8,
            "name": "organiclion897",
            "email": "olivia.sanchez@example.com"
        },
        {
            "id": 9,
            "name": "tinyostrich816",
            "email": "adryn.khwty@example.com"
        },
        {
            "id": 10,
            "name": "brownfrog618",
            "email": "sara.soto@example.com"
        }
    ],
    "subjects": [
        {
            "id": 1,
            "name": "Digital Signal Processing",
            "description": "Study of digital signals and their use.",
            "credits": 2
        },
        {
            "id": 2,
            "name": "Computer Organization and Architecture",
            "description": "Study of instruction set architecture (ISA) and processors.",
            "credits": 4
        },
        {
            "id": 3,
            "name": "Programming and Data Structures",
            "description": "Study of data organization and storage format that is usually chosen for efficient access to data.",
            "credits": 5
        },
        {
            "id": 4,
            "name": "Algorithms",
            "description": "",
            "credits": 1
        },
        {
            "id": 5,
            "name": "Theory of Computation",
            "description": "Study of models of computations and problems solvable by them.",
            "credits": 3
        },
        {
            "id": 6,
            "name": "Compiler Design",
            "description": "Study of stages of compilation and types of compilers.",
            "credits": 4
        },
        {
            "id": 7,
            "name": "Databases",
            "description": "Study of data storage and retreival software and design.",
            "credits": 3
        }
    ],
    "chapters": [
        {
            "id": 1,
            "name": "Boolean algebra",
            "description": "Algebra for boolean values",
            "order": 1,
            "subject": {
                "id": 1,
                "name": "Digital Signal Processing",
                "description": "Study of digital signals and their use.",
                "credits": 2
            }
        },
        {
            "id": 2,
            "name": "Combinational and sequential circuits",
            "description": "Types of circuits",
            "order": 2,
            "subject": {
                "id": 1,
                "name": "Digital Signal Processing",
                "description": "Study of digital signals and their use.",
                "credits": 2
            }
        },
        {
            "id": 3,
            "name": "Minimization",
            "description": null,
            "order": 3,
            "subject": {
                "id": 1,
                "name": "Digital Signal Processing",
                "description": "Study of digital signals and their use.",
                "credits": 2
            }
        },
        {
            "id": 4,
            "name": "ALU, data path and control unit",
            "description": "Architecture",
            "order": 1,
            "subject": {
                "id": 2,
                "name": "Computer Organization and Architecture",
                "description": "Study of instruction set architecture (ISA) and processors.",
                "credits": 4
            }
        },
        {
            "id": 5,
            "name": "Instruction pipelining, pipeline hazards",
            "description": null,
            "order": 2,
            "subject": {
                "id": 2,
                "name": "Computer Organization and Architecture",
                "description": "Study of instruction set architecture (ISA) and processors.",
                "credits": 4
            }
        },
        {
            "id": 6,
            "name": "Time Complexity",
            "description": "Big O notation",
            "order": 1,
            "subject": {
                "id": 3,
                "name": "Programming and Data Structures",
                "description": "Study of data organization and storage format that is usually chosen for efficient access to data.",
                "credits": 5
            }
        },
        {
            "id": 7,
            "name": "Space Complexity",
            "description": null,
            "order": 2,
            "subject": {
                "id": 3,
                "name": "Programming and Data Structures",
                "description": "Study of data organization and storage format that is usually chosen for efficient access to data.",
                "credits": 5
            }
        },
        {
            "id": 8,
            "name": "Linear Data Structures",
            "description": "Arrays vs Linked Lists vs Lists",
            "order": 3,
            "subject": {
                "id": 3,
                "name": "Programming and Data Structures",
                "description": "Study of data organization and storage format that is usually chosen for efficient access to data.",
                "credits": 5
            }
        },
        {
            "id": 9,
            "name": "Sorting I",
            "description": "Bubble sort, Insertion sort",
            "order": 1,
            "subject": {
                "id": 4,
                "name": "Algorithms",
                "description": "",
                "credits": 1
            }
        },
        {
            "id": 10,
            "name": "Sorting II",
            "description": "Quick sort, Merge sort",
            "order": 2,
            "subject": {
                "id": 4,
                "name": "Algorithms",
                "description": "",
                "credits": 1
            }
        },
        {
            "id": 11,
            "name": "Searching",
            "description": "Binary search",
            "order": 3,
            "subject": {
                "id": 4,
                "name": "Algorithms",
                "description": "",
                "credits": 1
            }
        },
        {
            "id": 12,
            "name": "State machine",
            "description": "Mealy and Moore",
            "order": 1,
            "subject": {
                "id": 5,
                "name": "Theory of Computation",
                "description": "Study of models of computations and problems solvable by them.",
                "credits": 3
            }
        },
        {
            "id": 13,
            "name": "Turing machine",
            "description": null,
            "order": 2,
            "subject": {
                "id": 5,
                "name": "Theory of Computation",
                "description": "Study of models of computations and problems solvable by them.",
                "credits": 3
            }
        },
        {
            "id": 14,
            "name": "Types of Compiler",
            "description": null,
            "order": 1,
            "subject": {
                "id": 6,
                "name": "Compiler Design",
                "description": "Study of stages of compilation and types of compilers.",
                "credits": 4
            }
        },
        {
            "id": 15,
            "name": "Phases of Compiler",
            "description": null,
            "order": 2,
            "subject": {
                "id": 6,
                "name": "Compiler Design",
                "description": "Study of stages of compilation and types of compilers.",
                "credits": 4
            }
        },
        {
            "id": 16,
            "name": "Types of databases",
            "description": "RDBMS vs No-SQL",
            "order": 1,
            "subject": {
                "id": 7,
                "name": "Databases",
                "description": "Study of data storage and retreival software and design.",
                "credits": 3
            }
        },
        {
            "id": 17,
            "name": "Normalisation",
            "description": null,
            "order": 2,
            "subject": {
                "id": 7,
                "name": "Databases",
                "description": "Study of data storage and retreival software and design.",
                "credits": 3
            }
        }
    ],
    "quizes": [
        {
            "id": 1,
            "dated": {
                "day": "31",
                "month": "1",
                "year": "2025",
                "hour": "14",
                "minute": "09"
            },
            "duration": 15,
            "description": "test quiz 1"
        },
        {
            "id": 2,
            "dated": {
                "day": "31",
                "month": "1",
                "year": "2025",
                "hour": "14",
                "minute": "02"
            },
            "duration": 10,
            "description": "test quiz 2"
        },
        {
            "id": 3,
            "dated": {
                "day": "31",
                "month": "1",
                "year": "2025",
                "hour": "17",
                "minute": "12"
            },
            "duration": 30,
            "description": "test quiz 3"
        },
        {
            "id": 4,
            "dated": {
                "day": "31",
                "month": "1",
                "year": "2025",
                "hour": "13",
                "minute": "52"
            },
            "duration": 15,
            "description": "test quiz 4"
        },
        {
            "id": 5,
            "dated": {
                "day": "14",
                "month": "2",
                "year": "2025",
                "hour": "00",
                "minute": "00"
            },
            "duration": 25,
            "description": "Valentines day quiz!"
        }
    ],
    "questions": [
        {
            "id": 1,
            "description": "Which among the following logic gates is an unary gate?",
            "options": [
                "XOR",
                "AND",
                "OR",
                "None of the above"
            ],
            "marks": 1,
            "correct": 3
        },
        {
            "id": 2,
            "description": "The output is '0' for like inputs and '1' for 'unlike inputs'. The statement is representative of which 2-input logic gate?",
            "options": [
                "NAND",
                "EX-NOR",
                "EX-OR",
                "NOR"
            ],
            "marks": 1,
            "correct": 2
        },
        {
            "id": 3,
            "description": "The output of a 2-input OR gate is zero only when its?",
            "options": [
                "Either input is 0",
                "Either input is 1",
                "Both inputs are 1",
                "Both inputs are 0"
            ],
            "marks": 1,
            "correct": 3
        },
        {
            "id": 4,
            "description": "The minterm expansion of f (P, Q, R) = PQ + QR\u0305 + PR\u0305 is?",
            "options": [
                "m2 + m4 + m6 + m7",
                "m0 + m1 + m6 + m7",
                "m2 + m3 + m4 + m5",
                "m0 + m1 + m3 + m7"
            ],
            "marks": 1,
            "correct": 0
        },
        {
            "id": 5,
            "description": "In Boolean algebra, (A.A\u0305) + A =?",
            "options": [
                "A",
                "A\u0305",
                "1",
                "0"
            ],
            "marks": 1,
            "correct": 0
        },
        {
            "id": 6,
            "description": "Algebra of logic is termed as ______________",
            "options": [
                "Numerical logic",
                "Boolean algebra",
                "Arithmetic logic",
                "Boolean number"
            ],
            "marks": 1,
            "correct": 1
        },
        {
            "id": 7,
            "description": "F(X,Y,Z,M) = X`Y`Z`M`. The degree of the function is ________",
            "options": [
                "2",
                "5",
                "4",
                "1"
            ],
            "marks": 1,
            "correct": 2
        },
        {
            "id": 8,
            "description": "A ________ value is represented by a Boolean expression.",
            "options": [
                "Positive",
                "Recursive",
                "Negative",
                "Boolean"
            ],
            "marks": 1,
            "correct": 3
        },
        {
            "id": 9,
            "description": "Which of the following is a Simplification law?",
            "options": [
                "M.(~M+N) = M.N",
                "M+(N.O) = (M+N)(M+O)",
                "~(M+N) = ~M.~N",
                "M.(N.O) = (M.N).O"
            ],
            "marks": 1,
            "correct": 0
        },
        {
            "id": 10,
            "description": "What are the canonical forms of Boolean Expressions?",
            "options": [
                "OR and XOR",
                "NOR and XNOR",
                "MAX and MIN",
                "SOM and POM"
            ],
            "marks": 1,
            "correct": 3
        }
    ],
    "responses": [
        {
            "marked": 3,
            "dated": {
                "day": "21",
                "month": "2",
                "year": "2025",
                "hour": "17",
                "minute": "13"
            }
        },
        {
            "marked": 0,
            "dated": {
                "day": "21",
                "month": "2",
                "year": "2025",
                "hour": "17",
                "minute": "13"
            }
        },
        {
            "marked": 3,
            "dated": {
                "day": "21",
                "month": "2",
                "year": "2025",
                "hour": "17",
                "minute": "13"
            }
        },
        {
            "marked": 1,
            "dated": {
                "day": "21",
                "month": "2",
                "year": "2025",
                "hour": "18",
                "minute": "19"
            }
        }
    ],
    "registered": [
        {
            "1": []
        },
        {
            "2": [
                1,
                3,
                4
            ]
        },
        {
            "3": [
                1,
                2,
                6,
                7
            ]
        },
        {
            "4": [
                1,
                4,
                5,
                7
            ]
        },
        {
            "5": [
                2,
                4,
                7
            ]
        },
        {
            "6": [
                1,
                2,
                4,
                7
            ]
        },
        {
            "7": [
                3,
                4,
                6,
                7
            ]
        },
        {
            "8": [
                1,
                2,
                3,
                4,
                5
            ]
        },
        {
            "9": [
                3
            ]
        },
        {
            "10": [
                1,
                4,
                5,
                7
            ]
        }
    ],
    "problem": [
        {
            "1": [
                1,
                3,
                5
            ]
        },
        {
            "2": [
                3,
                5
            ]
        },
        {
            "3": [
                1,
                3,
                4
            ]
        },
        {
            "4": [
                1,
                3
            ]
        },
        {
            "5": []
        }
    ]
}